selenium_gourmet/__init__.py
selenium_gourmet/__main__.py
selenium_gourmet/cli/__init__.py
selenium_gourmet/cli/main.py
selenium_gourmet/core/__init__.py
selenium_gourmet/core/generator.py
selenium_gourmet/core/installer.py
selenium_gourmet/gourmet/__init__.py
selenium_gourmet/gourmet/__main__.py
selenium_gourmet-0.2.2.dist-info/licenses/LICENSE
selenium_gourmet-0.2.2.dist-info/METADATA
selenium_gourmet-0.2.2.dist-info/WHEEL
selenium_gourmet-0.2.2.dist-info/entry_points.txt
selenium_gourmet-0.2.2.dist-info/top_level.txt
selenium_gourmet-0.2.2.dist-info/RECORD
