Metadata-Version: 2.4
Name: selenium-gourmet
Version: 0.2.2
Summary: Gerador de projetos Selenium com estrutura gourmet
Home-page: https://github.com/natan33/selenium-gourmet
Author: Natã Assis
Author-email: srassis2014@gmail.com
Classifier: Programming Language :: Python :: 3
Classifier: License :: OSI Approved :: MIT License
Classifier: Operating System :: OS Independent
Requires-Python: >=3.7
License-File: LICENSE
Requires-Dist: click>=8.1.7
Requires-Dist: selenium>=4.10.0
Dynamic: author
Dynamic: author-email
Dynamic: classifier
Dynamic: description
Dynamic: description-content-type
Dynamic: home-page
Dynamic: license-file
Dynamic: requires-dist
Dynamic: requires-python
Dynamic: summary
